odoo/addons/invader_payment_adyen_klarna_capture/README.rst
odoo/addons/invader_payment_adyen_klarna_capture/__init__.py
odoo/addons/invader_payment_adyen_klarna_capture/__manifest__.py
odoo/addons/invader_payment_adyen_klarna_capture/i18n/invader_payment_adyen_klarna_capture.pot
odoo/addons/invader_payment_adyen_klarna_capture/models/__init__.py
odoo/addons/invader_payment_adyen_klarna_capture/models/invader_payable.py
odoo/addons/invader_payment_adyen_klarna_capture/models/payment_acquirer.py
odoo/addons/invader_payment_adyen_klarna_capture/models/payment_transaction.py
odoo/addons/invader_payment_adyen_klarna_capture/readme/CONTRIBUTORS.rst
odoo/addons/invader_payment_adyen_klarna_capture/readme/DESCRIPTION.rst
odoo/addons/invader_payment_adyen_klarna_capture/readme/HISTORY.rst
odoo/addons/invader_payment_adyen_klarna_capture/security/ir_model_access.xml
odoo/addons/invader_payment_adyen_klarna_capture/static/description/index.html
odoo/addons/invader_payment_adyen_klarna_capture/wizards/__init__.py
odoo/addons/invader_payment_adyen_klarna_capture/wizards/adyen_klarna_capture_manual.py
odoo/addons/invader_payment_adyen_klarna_capture/wizards/adyen_klarna_capture_manual.xml
odoo14_addon_invader_payment_adyen_klarna_capture-14.0.1.0.2.dist-info/METADATA
odoo14_addon_invader_payment_adyen_klarna_capture-14.0.1.0.2.dist-info/WHEEL
odoo14_addon_invader_payment_adyen_klarna_capture-14.0.1.0.2.dist-info/top_level.txt
odoo14_addon_invader_payment_adyen_klarna_capture-14.0.1.0.2.dist-info/RECORD
